sitcom/README.md
sitcom/__init__.py
sitcom/__main__.py
sitcom/sfit.py
sitcom/sirgraf.py
sitcom/st1.py
sitcom/st2.py
sitcom/st3.py
sitcom/data/Sine_curve.png
sitcom/data/__init__.py
sitcom/data/black.png
sitcom/data/save.png
sitcom/data/save.png~
sitcom/data/white.png
sitcom/font/lato/Lato-Semibold.ttf
sitcom/font/lato/SIL Open Font License.txt
sitcom/icon/__init__.py
sitcom/icon/cme.ico
sitcom/icon/cme.png
sitcom/load/__init__.py
sitcom/load/sitcom.gif
sitcom-1.5.2.dist-info/LICENSE
sitcom-1.5.2.dist-info/METADATA
sitcom-1.5.2.dist-info/WHEEL
sitcom-1.5.2.dist-info/top_level.txt
sitcom-1.5.2.dist-info/RECORD
