Metadata-Version: 2.1
Name: sitcom
Version: 1.5.2
Summary: SITCoM: SiRGraF Integrated Tool for Coronal dynaMics
Home-page: https://github.com/pu3/SITCoM
Author: Purvi Udhwani, Arpit Shrivastava, Ritesh Patel
Author-email: purviaries@aries.res.in,arpits@aries.res.in,ritesh.sophy@gmail.com
License: MIT
Platform: any
Classifier: Programming Language :: Python :: 3
Classifier: License :: OSI Approved :: MIT License
Classifier: Operating System :: OS Independent
Requires-Python: >=3.6
License-File: LICENSE
Requires-Dist: PyQt5 (<6.0.0,>=5.15.0)
Requires-Dist: opencv-python
Requires-Dist: numpy (>=1.21.0)
Requires-Dist: matplotlib (>=3.5.3)
Requires-Dist: scikit-image (>=0.19.3)
Requires-Dist: sunpy (>=4.0.5)
Requires-Dist: astropy (>=5.1)
